{
    "JavaFlightRecorder": {
        "JavaFlightRecorder_Mandelbrot.jfr": {
            "java.lang.invoke.InvokerBytecodeGenerator.emitImplicitConversion(Ljava/lang/invoke/LambdaForm$BasicType;Ljava/lang/Class;Ljava/lang/Object;)V": "0.004123881397171018",
            "jdk.jfr.internal.handlers.EventHandler1361_1687197124446-2779966.write(JJJ)V": "0.004123881397171018",
            "java.lang.invoke.InvokerBytecodeGenerator.resolveInvokerMember(Ljava/lang/Class;Ljava/lang/String;Ljava/lang/invoke/MethodType;)Ljava/lang/invoke/MemberName;": "0.004123881397171018",
            "jdk.jfr.internal.RequestEngine.run_requests(Ljava/util/Collection;)J": "0.004123881397171018",
            "Mandelbrot.mandelbrot(I)I": "99.95463730463112",
            "java.nio.CharBuffer.limit(I)Ljava/nio/Buffer;": "0.004123881397171018",
            "java.lang.StringCoding.implEncodeAsciiArray([CI[BII)I": "0.004123881397171018",
            "jdk.internal.misc.Unsafe.putAddress(Ljava/lang/Object;JJ)V": "0.004123881397171018",
            "java.lang.invoke.InvokerBytecodeGenerator.getInternalName(Ljava/lang/Class;)Ljava/lang/String;": "0.004123881397171018",
            "java.io.BufferedWriter.ensureOpen()V": "0.004123881397171018"
        },
        "JavaFlightRecorder_Queens.jfr": {
            "java.util.Arrays.fill([II)V": "0.35892527517604433",
            "java.lang.invoke.LambdaForm$MH+0x000000080100e000.1197365356.invoke(Ljava/lang/Object;Ljava/lang/Object;J)Ljava/lang/Object;": "0.003418335954057565",
            "Queens.benchmark()Ljava/lang/Object;": "0.037601695494633214",
            "java.lang.invoke.DirectMethodHandle.makePreparedLambdaForm(Ljava/lang/invoke/MethodType;I)Ljava/lang/invoke/LambdaForm;": "0.003418335954057565",
            "Queens.placeQueen(I)Z": "13.717782183633009",
            "Queens.getRowColumn(II)Z": "57.588705818007796",
            "java.util.Arrays.fill([ZZ)V": "0.526423736924865",
            "Queens.setRowColumn(IIZ)V": "26.977507349422304",
            "Benchmark.innerBenchmarkLoop(I)Z": "0.05469337526492104",
            "Queens.queens()Z": "0.707595542489916"
        },
        "JavaFlightRecorder_Bounce.jfr": {
            "java.lang.invoke.InvokerBytecodeGenerator.isStaticallyInvocable(Ljava/lang/invoke/MemberName;)Z": "0.007064142413111049",
            "Bounce.lambda$benchmark$0(Lsom/Random;I)LBounce$Ball;": "0.37439954789488555",
            "java.util.Arrays.setAll([Ljava/lang/Object;Ljava/util/function/IntFunction;)V": "1.4587454083074316",
            "Run.printResult(J)V": "0.0035320712065555243",
            "Bounce$Ball.bounce()Z": "85.18649335970613",
            "Bounce.benchmark()Ljava/lang/Object;": "8.300367335405483",
            "som.Random.next()I": "1.3527832721107658",
            "java.lang.invoke.DirectMethodHandle$Holder.newInvokeSpecial(Ljava/lang/Object;Ljava/lang/Object;)Ljava/lang/Object;": "0.05651313930488839",
            "Benchmark.innerBenchmarkLoop(I)Z": "0.03178864085899972",
            "Bounce$Ball.<init>(Lsom/Random;)V": "3.1717999434868607"
        },
        "JavaFlightRecorder_Havlak.jfr": {
            "havlak.HavlakLoopFinder.lambda$processEdges$1(ILhavlak/BasicBlock;)V": "7.68854178808719",
            "som.IdentitySet.lambda$contains$0(Ljava/lang/Object;Ljava/lang/Object;)Z": "38.10001165637021",
            "havlak.HavlakLoopFinder.doDFS(Lhavlak/BasicBlock;I)I": "5.713952675136962",
            "havlak.HavlakLoopFinder.lambda$initAllNodes$0(Lhavlak/BasicBlock;)V": "16.822473481757783",
            "som.Vector.forEach(Lsom/ForEachInterface;)V": "2.2706609161906983",
            "som.Vector.<init>(I)V": "4.9003380347359835",
            "havlak.HavlakLoopFinder.findLoops()V": "4.063410653922369",
            "havlak.HavlakLoopFinder.lambda$stepEProcessNonBackPreds$4(ILsom/Vector;Lsom/Vector;Ljava/lang/Integer;)V": "4.161324163655438",
            "som.Vector.hasSome(Lsom/TestInterface;)Z": "2.844154330341532",
            "som.Vector.append(Ljava/lang/Object;)V": "2.5131134164821076"
        },
        "JavaFlightRecorder_CD.jfr": {
            "cd.CollisionDetector.recurse(Lcd/RedBlackTree;Lcd/RedBlackTree;Lcd/Vector2D;Lcd/Motion;)V": "12.242242636912037",
            "cd.RedBlackTree.findNode(Ljava/lang/Comparable;)Lcd/RedBlackTree$Node;": "7.700193194811339",
            "cd.RedBlackTree.leftRotate(Lcd/RedBlackTree$Node;)Lcd/RedBlackTree$Node;": "2.949177936363995",
            "cd.CollisionDetector.lambda$handleNewFrame$0(Lcd/RedBlackTree;Lsom/Vector;Lcd/Aircraft;)V": "2.306509482316761",
            "cd.RedBlackTree.forEach(Lsom/ForEachInterface;)V": "6.119149942830107",
            "cd.CollisionDetector.isInVoxel(Lcd/Vector2D;Lcd/Motion;)Z": "15.56992469345109",
            "cd.RedBlackTree.treeMinimum(Lcd/RedBlackTree$Node;)Lcd/RedBlackTree$Node;": "7.136379765800576",
            "cd.RedBlackTree.put(Ljava/lang/Comparable;Ljava/lang/Object;)Ljava/lang/Object;": "7.731735204825927",
            "cd.Vector2D.compareNumbers(DD)I": "3.4696211016047",
            "cd.RedBlackTree.treeInsert(Ljava/lang/Comparable;Ljava/lang/Object;)Lcd/RedBlackTree$InsertResult;": "21.85861294010961"
        },
        "JavaFlightRecorder_List.jfr": {
            "List.isShorterThan(LList$Element;LList$Element;)Z": "86.22527773626264",
            "List.verifyResult(Ljava/lang/Object;)Z": "0.007472724555372888",
            "List$Element.getNext()LList$Element;": "10.110596323419518",
            "List$Element.<init>(Ljava/lang/Object;)V": "0.16190903203307924",
            "List.benchmark()Ljava/lang/Object;": "0.01245454092562148",
            "List.tail(LList$Element;LList$Element;LList$Element;)LList$Element;": "2.3937627659044485",
            "List$Element.length()I": "0.08219997010910177",
            "Benchmark.innerBenchmarkLoop(I)Z": "0.007472724555372888",
            "List$Element.setNext(LList$Element;)V": "0.022418173666118667",
            "List.makeList(I)LList$Element;": "0.9465451103472325"
        },
        "JavaFlightRecorder_DeltaBlue.jfr": {
            "deltablue.Planner.addPropagate(Ldeltablue/AbstractConstraint;I)Z": "3.2451208921797154",
            "som.Vector.forEach(Lsom/ForEachInterface;)V": "10.818593171534348",
            "deltablue.ScaleConstraint.execute()V": "10.347822112527995",
            "deltablue.AbstractConstraint.<init>(Ldeltablue/Strength$Sym;)V": "17.866447278211982",
            "deltablue.AbstractConstraint.satisfy(ILdeltablue/Planner;)Ldeltablue/AbstractConstraint;": "3.1948443713149595",
            "deltablue.Plan$$Lambda$82+0x0000000801014220.111156771.apply(Ljava/lang/Object;)V": "13.574660633484163",
            "som.Vector.<init>(I)V": "8.894373600255953",
            "deltablue.Planner$$Lambda$79+0x000000080100f388.1262773598.apply(Ljava/lang/Object;)V": "4.639151697975227",
            "deltablue.Planner$$Lambda$84+0x0000000801014668.2039810346.apply(Ljava/lang/Object;)V": "2.31729055258467",
            "som.Vector.append(Ljava/lang/Object;)V": "2.573243749714338"
        },
        "JavaFlightRecorder_Storage.jfr": {
            "Storage$$Lambda$76+0x000000080100e000.1653986196.apply(I)Ljava/lang/Object;": "0.4507971412864211",
            "java.util.Arrays.setAll([Ljava/lang/Object;Ljava/util/function/IntFunction;)V": "35.09620670698186",
            "Storage$$Lambda$76+0x000000080100e000.1653986196.<init>(LStorage;ILsom/Random;)V": "0.8282939343961884",
            "Storage.lambda$buildTreeDepth$0(ILsom/Random;I)Ljava/lang/Object;": "3.67601246105919",
            "Storage.benchmark()Ljava/lang/Object;": "0.01832508704416346",
            "Storage.buildTreeDepth(ILsom/Random;)Ljava/lang/Object;": "45.03573391973612",
            "som.Random.next()I": "12.926516400952906",
            "java.lang.invoke.LambdaForm$DMH+0x000000080100c400.1197365356.newInvokeSpecial(Ljava/lang/Object;Ljava/lang/Object;ILjava/lang/Object;)Ljava/lang/Object;": "1.2314458493677845",
            "Benchmark.innerBenchmarkLoop(I)Z": "0.01832508704416346",
            "java.lang.invoke.DirectMethodHandle.allocateInstance(Ljava/lang/Object;)Ljava/lang/Object;": "0.678028220634048"
        },
        "JavaFlightRecorder_Sieve.jfr": {
            "java.lang.invoke.LambdaForm$MH+0x000000080100e000.1197365356.invoke(Ljava/lang/Object;Ljava/lang/Object;J)Ljava/lang/Object;": "0.0034151839076534273",
            "java.lang.invoke.DirectMethodHandle$Holder.invokeStatic(Ljava/lang/Object;JJ)J": "0.0034151839076534273",
            "Run.measure(LBenchmark;)V": "0.010245551722960282",
            "java.lang.Integer.valueOf(I)Ljava/lang/Integer;": "0.0034151839076534273",
            "Sieve.benchmark()Ljava/lang/Object;": "3.6269253099279397",
            "java.lang.invoke.BootstrapMethodInvoker.invoke(Ljava/lang/Class;Ljava/lang/invoke/MethodHandle;Ljava/lang/String;Ljava/lang/Object;Ljava/lang/Object;Ljava/lang/Class;)Ljava/lang/Object;": "0.0034151839076534273",
            "java.util.Arrays.fill([ZZ)V": "5.556504217752126",
            "Sieve.sieve([ZI)I": "90.72094532290564",
            "Benchmark.innerBenchmarkLoop(I)Z": "0.013660735630613709",
            "java.nio.ByteBuffer.hasArray()Z": "0.0068303678153068545"
        },
        "JavaFlightRecorder_Towers.jfr": {
            "Towers.buildTowerAt(II)V": "0.05909343715239154",
            "java.lang.invoke.InvokerBytecodeGenerator.emitImplicitConversion(Ljava/lang/invoke/LambdaForm$BasicType;Ljava/lang/Class;Ljava/lang/Object;)V": "0.006952169076751946",
            "Towers$TowersDisk.setNext(LTowers$TowersDisk;)V": "16.98067296996663",
            "Towers$TowersDisk.getNext()LTowers$TowersDisk;": "4.171301446051167",
            "Towers.moveDisks(III)V": "4.046162402669633",
            "Towers$TowersDisk.getSize()I": "11.846496106785317",
            "Towers.benchmark()Ljava/lang/Object;": "0.05561735261401557",
            "Towers.pushDisk(LTowers$TowersDisk;I)V": "38.20216907675194",
            "Towers.popDiskFrom(I)LTowers$TowersDisk;": "19.987486095661847",
            "Towers.moveTopDisk(II)V": "4.5675750834260285"
        },
        "JavaFlightRecorder_NBody.jfr": {
            "nbody.Body.setY(D)V": "1.8822461237603016",
            "nbody.Body.getMass()D": "0.5936583321692974",
            "nbody.Body.setVX(D)V": "29.58862969688504",
            "nbody.NBodySystem.advance(D)V": "41.14750663500489",
            "nbody.Body.getY()D": "0.8590585277273363",
            "nbody.Body.getZ()D": "8.007403268612935",
            "nbody.Body.setVZ(D)V": "9.18075150160637",
            "nbody.Body.getVZ()D": "0.4225450481910881",
            "nbody.Body.setVY(D)V": "6.0588070959631235",
            "nbody.Body.setX(D)V": "1.166364017320855"
        },
        "JavaFlightRecorder_Richards.jfr": {
            "richards.TaskState.isTaskHoldingOrWaiting()Z": "5.596959308391713",
            "richards.Scheduler.schedule()V": "11.00014905351021",
            "richards.Packet.<init>(Lrichards/Packet;II)V": "12.751527798479655",
            "richards.TaskControlBlock.<init>(Lrichards/TaskControlBlock;IILrichards/Packet;Lrichards/TaskState;Lrichards/ProcessFunction;Lrichards/RBObject;)V": "6.327321508421523",
            "richards.HandlerTaskDataRecord.workInAdd(Lrichards/Packet;)V": "3.912654643016843",
            "Richards.benchmark()Ljava/lang/Object;": "9.479803249366523",
            "richards.Packet.setLink(Lrichards/Packet;)V": "4.367267849157848",
            "richards.RBObject.append(Lrichards/Packet;Lrichards/Packet;)Lrichards/Packet;": "5.0081979430615595",
            "richards.TaskControlBlock.runTask()Lrichards/TaskControlBlock;": "3.8232225368907438",
            "richards.RBObject.<init>()V": "11.04486510657326"
        },
        "JavaFlightRecorder_Json.jfr": {
            "java.lang.String.length()I": "3.656528477334367",
            "java.lang.StringLatin1.newString([BII)Ljava/lang/String;": "3.2061216582719876",
            "java.lang.String.equals(Ljava/lang/Object;)Z": "25.174351026733824",
            "json.JsonPureStringParser.endCapture()Ljava/lang/String;": "5.25958930647036",
            "json.JsonPureStringParser.readStringInternal()Ljava/lang/String;": "10.325455249903138",
            "java.lang.String.<init>([BB)V": "5.114296784192174",
            "java.lang.String.substring(II)Ljava/lang/String;": "3.738860906625339",
            "json.JsonPureStringParser.readArray()Ljson/JsonArray;": "2.513560635412631",
            "json.JsonPureStringParser.read()V": "14.989345215032934",
            "java.util.Arrays.copyOfRange([BII)[B": "7.211352189074002"
        },
        "JavaFlightRecorder_Permute.jfr": {
            "java.lang.CharacterDataLatin1.toUpperCase(I)I": "0.003615721155584481",
            "sun.nio.cs.StreamEncoder.write([CII)V": "0.003615721155584481",
            "Permute.swap(II)V": "44.285352713598726",
            "java.lang.Integer.valueOf(I)Ljava/lang/Integer;": "0.010847163466753443",
            "java.lang.System$2.encodeASCII([CI[BII)I": "0.003615721155584481",
            "jdk.jfr.events.ExceptionStatisticsEvent.commit()V": "0.003615721155584481",
            "java.lang.StringLatin1.inflate([BI[CII)V": "0.003615721155584481",
            "Permute.permute(I)V": "55.591712767111396",
            "Benchmark.innerBenchmarkLoop(I)Z": "0.010847163466753443",
            "Permute.benchmark()Ljava/lang/Object;": "0.05423581733376722"
        }
    },
    "HonestProfiler": {
        "Richards.hpl": {
            "richards.Packet::<init>": "6.9",
            "richards.TaskControlBlock::addInputAndCheckPriority": "2.2",
            "Richards::benchmark": "4.5",
            "richards.RBObject::append": "3.3",
            "AGCT::Unknown Java[ERR=-5]": "44.6",
            "richards.HandlerTaskDataRecord::workInAdd": "2.2",
            "richards.TaskControlBlock::<init>": "3.1",
            "richards.Scheduler::schedule": "5.7",
            "richards.TaskState::isTaskHoldingOrWaiting": "2.7",
            "richards.RBObject::<init>": "6.2"
        },
        "Mandelbrot.hpl": {
            "java.lang.invoke.StringConcatFactory::generateMHInlineCopy": "0.0",
            "AGCT::Not walkable Java[ERR=-6]": "0.0",
            "java.lang.ClassLoader::defineClass1": "0.0",
            "java.lang.ClassLoader::defineClass0": "0.0",
            "java.lang.Class::isPrimitive": "0.0",
            "AGCT::Unknown not Java[ERR=-3]": "1.8",
            "jdk.internal.org.objectweb.asm.ClassWriter::visitMethod": "0.0",
            "AGCT::Unknown Java[ERR=-5]": "0.0",
            "Mandelbrot::mandelbrot": "98.0",
            "sun.invoke.util.BytecodeDescriptor::unparseSig": "0.0"
        },
        "List.hpl": {
            "List$Element::getNext": "9.3",
            "List::makeList": "0.7",
            "java.lang.Integer::valueOf": "0.0",
            "List::tail": "1.9",
            "List::isShorterThan": "82.6",
            "AGCT::Unknown not Java[ERR=-3]": "2.4",
            "List$Element::<init>": "0.1",
            "AGCT::Unknown Java[ERR=-5]": "2.7",
            "List$Element::setNext": "0.0",
            "List$Element::length": "0.1"
        },
        "Json.hpl": {
            "json.JsonPureStringParser::read": "16.1",
            "java.lang.String::<init>": "5.3",
            "json.JsonPureStringParser::readArray": "2.6",
            "java.lang.String::length": "3.2",
            "java.util.Arrays::copyOfRange": "7.0",
            "java.lang.String::equals": "22.6",
            "AGCT::Unknown not Java[ERR=-3]": "4.0",
            "AGCT::Unknown Java[ERR=-5]": "10.5",
            "java.lang.String::isLatin1": "2.4",
            "json.JsonPureStringParser::readStringInternal": "8.7"
        },
        "Havlak.hpl": {
            "som.IdentitySet::lambda$contains$0": "34.4",
            "havlak.HavlakLoopFinder::lambda$initAllNodes$0": "11.7",
            "havlak.HavlakLoopFinder::findLoops": "6.0",
            "havlak.HavlakLoopFinder::lambda$stepEProcessNonBackPreds$4": "3.9",
            "som.Vector::append": "3.5",
            "AGCT::Unknown not Java[ERR=-3]": "7.8",
            "havlak.HavlakLoopFinder::lambda$processEdges$1": "6.7",
            "havlak.HavlakLoopFinder::doDFS": "5.4",
            "som.Vector::hasSome": "2.1",
            "som.Vector::forEach": "2.3"
        },
        "Permute.hpl": {
            "Permute::swap": "40.0",
            "Permute::permute": "51.8",
            "Permute::verifyResult": "0.0",
            "Permute::benchmark": "0.0",
            "java.io.FileOutputStream::writeBytes": "0.0",
            "AGCT::Not walkable Java[ERR=-6]": "0.0",
            "Benchmark::innerBenchmarkLoop": "0.0",
            "java.lang.ClassLoader::defineClass0": "0.0",
            "AGCT::Unknown not Java[ERR=-3]": "2.2",
            "AGCT::Unknown Java[ERR=-5]": "5.9"
        },
        "Queens.hpl": {
            "Queens::getRowColumn": "66.3",
            "Benchmark::innerBenchmarkLoop": "0.0",
            "Queens::benchmark": "0.0",
            "AGCT::Unknown not Java[ERR=-3]": "3.4",
            "AGCT::Unknown Java[ERR=-5]": "0.7",
            "Queens::placeQueen": "8.4",
            "Queens::setRowColumn": "19.8",
            "Queens::queens": "0.6",
            "java.util.Arrays::fill": "0.2"
        },
        "Storage.hpl": {
            "java.lang.invoke.LambdaForm$DMH.0x0000000801006800::newInvokeSpecial": "1.0",
            "java.lang.invoke.DirectMethodHandle::allocateInstance": "0.5",
            "Storage::buildTreeDepth": "41.6",
            "java.util.Arrays::setAll": "33.8",
            "som.Random::next": "13.2",
            "AGCT::Unknown not Java[ERR=-3]": "3.8",
            "AGCT::Unknown Java[ERR=-5]": "1.9",
            "Storage$$Lambda$2.0x00000008010030f0::apply": "0.7",
            "Storage$$Lambda$2.0x00000008010030f0::<init>": "0.5",
            "Storage::lambda$buildTreeDepth$0": "3.0"
        },
        "Sieve.hpl": {
            "java.io.FileOutputStream::writeBytes": "0.0",
            "Sieve::benchmark": "3.0",
            "AGCT::Not walkable Java[ERR=-6]": "0.0",
            "Benchmark::innerBenchmarkLoop": "0.0",
            "java.lang.ClassLoader::defineClass0": "0.0",
            "Sieve::sieve": "89.6",
            "AGCT::Unknown not Java[ERR=-3]": "2.0",
            "AGCT::Unknown Java[ERR=-5]": "0.0",
            "java.util.Arrays::fill": "5.2",
            "java.lang.String::getChars": "0.0"
        },
        "DeltaBlue.hpl": {
            "deltablue.ScaleConstraint::execute": "9.0",
            "deltablue.Plan$$Lambda$8.0x000000080100d938::apply": "8.2",
            "deltablue.Variable::<init>": "5.4",
            "deltablue.Planner::incrementalAdd": "14.2",
            "AGCT::Unknown not Java[ERR=-3]": "5.8",
            "AGCT::Unknown Java[ERR=-5]": "10.6",
            "deltablue.AbstractConstraint::satisfy": "2.7",
            "som.Vector::forEach": "10.7",
            "deltablue.Planner$$Lambda$5.0x000000080100cbb0::apply": "3.8",
            "som.Dictionary::at": "3.6"
        },
        "Bounce.hpl": {
            "Bounce::benchmark": "8.8",
            "Bounce$Ball::bounce": "83.1",
            "java.util.Arrays::setAll": "1.2",
            "Bounce::lambda$benchmark$0": "0.3",
            "Benchmark::innerBenchmarkLoop": "0.0",
            "AGCT::Not walkable Java[ERR=-6]": "0.0",
            "som.Random::next": "1.3",
            "AGCT::Unknown not Java[ERR=-3]": "2.0",
            "Bounce$Ball::<init>": "3.0",
            "java.lang.invoke.DirectMethodHandle$Holder::newInvokeSpecial": "0.0"
        },
        "NBody.hpl": {
            "nbody.Body::setY": "1.6",
            "nbody.Body::setX": "1.2",
            "nbody.Body::getY": "0.7",
            "nbody.Body::setVZ": "9.1",
            "nbody.Body::getZ": "7.8",
            "nbody.Body::setVX": "27.7",
            "nbody.Body::setVY": "5.8",
            "nbody.Body::getMass": "0.5",
            "AGCT::Unknown not Java[ERR=-3]": "2.0",
            "nbody.NBodySystem::advance": "41.6"
        },
        "Towers.hpl": {
            "Towers$TowersDisk::getSize": "8.6",
            "Towers::popDiskFrom": "23.1",
            "Towers::moveDisks": "3.7",
            "Towers::buildTowerAt": "0.0",
            "AGCT::Unknown not Java[ERR=-3]": "4.1",
            "Towers::pushDisk": "34.1",
            "Towers$TowersDisk::setNext": "15.1",
            "AGCT::Unknown Java[ERR=-5]": "3.6",
            "Towers::moveTopDisk": "4.6",
            "Towers$TowersDisk::getNext": "2.9"
        },
        "CD.hpl": {
            "cd.CollisionDetector::recurse": "11.1",
            "cd.RedBlackTree::forEach": "4.8",
            "cd.RedBlackTree::put": "7.2",
            "cd.RedBlackTree::findNode": "8.1",
            "cd.RedBlackTree::treeMinimum": "6.3",
            "AGCT::Unknown not Java[ERR=-3]": "5.1",
            "AGCT::Unknown Java[ERR=-5]": "3.7",
            "cd.Vector2D::compareNumbers": "3.3",
            "cd.RedBlackTree::treeInsert": "20.5",
            "cd.CollisionDetector::isInVoxel": "14.1"
        }
    },
    "Async": {
        "rebench_test_Async_DeltaBlue.txt": {
            "deltablue.Strength.stronger": "13.39%",
            "deltablue.Planner$$Lambda$5.0x000000080100cbb0.apply": "3.83%",
            "deltablue.AbstractConstraint.satisfy": "5.25%",
            "deltablue.Plan$$Lambda$8.0x000000080100d938.apply": "11.46%",
            "deltablue.Variable.<init>": "6.94%",
            "som.Vector.forEach": "8.80%",
            "deltablue.Planner.addPropagate": "3.16%",
            "itable": "3.06%",
            "G1ParScanThreadState::trim_queue_to_threshold(unsigned": "3.39%",
            "deltablue.ScaleConstraint.execute": "6.42%"
        },
        "rebench_test_Async_Bounce.txt": {
            "Bounce$Ball.bounce": "83.92%",
            "som.Random.next": "1.47%",
            "clear_page_rep_[k]": "0.10%",
            "java.util.Arrays.setAll": "1.29%",
            "SpinPause": "0.03%",
            "Bounce.benchmark": "8.87%",
            "java.lang.invoke.DirectMethodHandle$Holder.newInvokeSpecial": "0.07%",
            "_raw_spin_unlock_irqrestore_[k]": "0.04%",
            "Bounce$Ball.<init>": "3.26%",
            "Bounce.lambda$benchmark$0": "0.30%"
        },
        "rebench_test_Async_Mandelbrot.txt": {
            "DebugInformationRecorder::find_sharable_decode_offset(int)": "0.01%",
            "java.nio.charset.CharsetEncoder.encode": "0.01%",
            "Mandelbrot.mandelbrot": "99.50%",
            "java.lang.String.hashCode": "0.01%",
            "java.lang.invoke.MemberName.getMethodType": "0.01%",
            "InstanceKlass::find_method_index(Array<Method*>": "0.01%",
            "LinearScan::allocate_registers()": "0.01%",
            "Monitor::wait_without_safepoint_check(long)": "0.00%",
            "_raw_spin_unlock_irqrestore_[k]": "0.02%",
            "GlobalValueNumbering::GlobalValueNumbering(IR*)": "0.01%"
        },
        "rebench_test_Async_Storage.txt": {
            "java.lang.invoke.DirectMethodHandle.allocateInstance": "0.53%",
            "som.Random.next": "13.29%",
            "java.util.Arrays.setAll": "35.90%",
            "Storage.lambda$buildTreeDepth$0": "3.07%",
            "Storage$$Lambda$2.0x00000008010030f0.apply": "0.51%",
            "SpinPause": "0.25%",
            "Storage$$Lambda$2.0x00000008010030f0.<init>": "0.53%",
            "G1ParScanThreadState::trim_queue_to_threshold(unsigned": "0.18%",
            "Storage.buildTreeDepth": "42.89%",
            "java.lang.invoke.LambdaForm$DMH.0x0000000801006800.newInvokeSpecial": "0.95%"
        },
        "rebench_test_Async_Towers.txt": {
            "Towers$TowersDisk.setNext": "15.58%",
            "Towers.popDiskFrom": "23.35%",
            "Towers.moveDisks": "7.68%",
            "clear_page_rep_[k]": "0.05%",
            "Towers.pushDisk": "35.45%",
            "Towers.moveTopDisk": "4.37%",
            "Towers$TowersDisk.getSize": "9.62%",
            "Towers.buildTowerAt": "0.02%",
            "Towers$TowersDisk.getNext": "3.39%",
            "Towers.benchmark": "0.03%"
        },
        "rebench_test_Async_CD.txt": {
            "cd.CollisionDetector.recurse": "11.59%",
            "cd.CollisionDetector.isInVoxel": "14.40%",
            "cd.RedBlackTree.forEach": "5.03%",
            "cd.RedBlackTree.put": "7.22%",
            "cd.RedBlackTree.treeInsert": "21.15%",
            "cd.RedBlackTree.findNode": "8.09%",
            "cd.RedBlackTree.treeMinimum": "6.26%",
            "cd.CollisionDetector.lambda$handleNewFrame$0": "2.04%",
            "cd.Vector2D.compareNumbers": "3.00%",
            "cd.RedBlackTree.leftRotate": "2.49%"
        },
        "rebench_test_Async_Havlak.txt": {
            "havlak.HavlakLoopFinder.findLoops": "5.69%",
            "havlak.HavlakLoopFinder.lambda$initAllNodes$0": "11.16%",
            "som.Vector.hasSome": "2.25%",
            "som.Vector.append": "3.13%",
            "som.Vector.forEach": "2.18%",
            "som.IdentitySet.lambda$contains$0": "32.44%",
            "G1ParScanThreadState::trim_queue_to_threshold(unsigned": "7.17%",
            "havlak.HavlakLoopFinder.lambda$processEdges$1": "6.03%",
            "havlak.HavlakLoopFinder.lambda$stepEProcessNonBackPreds$4": "3.86%",
            "havlak.HavlakLoopFinder.doDFS": "6.20%"
        },
        "rebench_test_Async_Sieve.txt": {
            "java.util.Arrays.fill": "5.01%",
            "Sieve.benchmark": "3.17%",
            "Interpreter": "0.02%",
            "clear_page_rep_[k]": "0.13%",
            "Sieve.sieve": "90.78%",
            "SpinPause": "0.06%",
            "HeapRegionManager::par_iterate(HeapRegionClosure*,": "0.02%",
            "G1ParScanThreadState::trim_queue_to_threshold(unsigned": "0.02%",
            "__memset_avx2_unaligned_erms": "0.04%",
            "_raw_spin_unlock_irqrestore_[k]": "0.04%"
        },
        "rebench_test_Async_Permute.txt": {
            "Permute.permute": "58.33%",
            "Permute.swap": "41.21%",
            "DebugInformationRecorder::find_sharable_decode_offset(int)": "0.01%",
            "Permute.benchmark": "0.02%",
            "Interpreter": "0.01%",
            "clear_page_rep_[k]": "0.01%",
            "Permute.verifyResult": "0.01%",
            "Benchmark.innerBenchmarkLoop": "0.02%",
            "[vdso]": "0.01%",
            "_IO_default_xsputn": "0.01%"
        },
        "rebench_test_Async_NBody.txt": {
            "nbody.Body.setVZ": "8.55%",
            "nbody.Body.getZ": "7.97%",
            "nbody.Body.getY": "0.82%",
            "nbody.Body.setX": "1.15%",
            "nbody.Body.setY": "1.91%",
            "nbody.Body.setVX": "28.58%",
            "nbody.Body.setVY": "5.91%",
            "nbody.Body.getMass": "0.48%",
            "nbody.Body.getVZ": "0.44%",
            "nbody.NBodySystem.advance": "42.67%"
        },
        "rebench_test_Async_List.txt": {
            "List$Element.getNext": "9.71%",
            "List.makeList": "0.74%",
            "clear_page_rep_[k]": "0.07%",
            "List$Element.setNext": "0.03%",
            "java.lang.Integer.valueOf": "0.02%",
            "List.tail": "5.04%",
            "List$Element.length": "0.10%",
            "List.isShorterThan": "83.74%",
            "__memset_avx2_unaligned_erms": "0.01%",
            "List$Element.<init>": "0.14%"
        },
        "rebench_test_Async_Json.txt": {
            "jbyte_disjoint_arraycopy": "7.53%",
            "java.lang.String.length": "3.20%",
            "java.lang.String.substring": "2.70%",
            "java.lang.String.<init>": "4.26%",
            "java.lang.String.isLatin1": "2.66%",
            "json.JsonPureStringParser.readStringInternal": "9.53%",
            "java.util.Arrays.copyOfRange": "7.82%",
            "java.lang.String.equals": "20.13%",
            "json.JsonPureStringParser.read": "14.14%",
            "json.JsonPureStringParser.readValue": "2.77%"
        },
        "rebench_test_Async_Queens.txt": {
            "java.util.Arrays.fill": "0.63%",
            "Queens.getRowColumn": "59.07%",
            "Queens.setRowColumn": "23.54%",
            "clear_page_rep_[k]": "0.09%",
            "Queens.queens": "0.49%",
            "Queens.placeQueen": "15.63%",
            "_raw_spin_unlock_irqrestore_[k]": "0.02%",
            "__tls_get_addr": "0.01%",
            "Queens.benchmark": "0.05%",
            "Benchmark.innerBenchmarkLoop": "0.02%"
        },
        "rebench_test_Async_Richards.txt": {
            "richards.Scheduler.schedule": "6.41%",
            "Richards.benchmark": "5.49%",
            "richards.Packet.<init>": "7.73%",
            "richards.TaskState.isTaskHoldingOrWaiting": "3.02%",
            "itable": "34.48%",
            "richards.Scheduler$$Lambda$4.0x0000000801006a28.apply": "3.11%",
            "richards.TaskControlBlock.<init>": "3.01%",
            "richards.Scheduler$$Lambda$5.0x0000000801006c50.apply": "3.51%",
            "richards.RBObject.<init>": "6.46%",
            "richards.RBObject.append": "3.53%"
        }
    },
    "JProfiler": {
        "JProfiler_Towers.txt": {
            "Run.reportBenchmark": "0.1",
            "Towers$TowersDisk.<init>": "3.8",
            "Towers.moveDisks": "94.6",
            "java.io.PrintStream.println": "0.1",
            "Run.lambda$getSuiteFromName$13": "0.1",
            "Towers.moveTopDisk": "0.2",
            "java.lang.Integer.valueOf": "0.4",
            "Towers.buildTowerAt": "0.1",
            "Towers.benchmark": "0.4",
            "Run.printResult": "0.1"
        },
        "JProfiler_Sieve.txt": {
            "Run.reportBenchmark": "0.1",
            " ": "0",
            "Sieve.benchmark": "4.6",
            "java.io.PrintStream.println": "0.1",
            "Sieve.sieve": "94.8",
            "java.lang.Integer.valueOf": "0.2",
            "Run.getSuiteFromName": "0.1",
            "Run.runBenchmark": "0.1",
            "Benchmark.innerBenchmarkLoop": "0.1",
            "Run.printResult": "0.1"
        },
        "JProfiler_DeltaBlue.txt": {
            "deltablue.AbstractConstraint.inputsKnown": "4.5",
            "deltablue.AbstractConstraint.satisfy": "11.4",
            "deltablue.Planner.removePropagateFrom": "9.0",
            "som.Vector.<init>": "29.0",
            "deltablue.Variable.<init>": "5.1",
            "som.Vector.forEach": "7.0",
            "deltablue.Planner.addPropagate": "1.6",
            "deltablue.Planner.constraintsConsuming": "5.3",
            "deltablue.AbstractConstraint.<init>": "5.1",
            "deltablue.Planner.addConstraintsConsumingTo": "17.7"
        },
        "JProfiler_Havlak.txt": {
            "havlak.HavlakLoopFinder.findLoops": "4.1",
            "havlak.UnionFindNode.<init>": "3.5",
            "som.Vector.<init>": "42.4",
            "havlak.HavlakLoopFinder.stepD": "3.5",
            "java.lang.Integer.valueOf": "8.7",
            "som.Set.<init>": "5.1",
            "havlak.UnionFindNode.findSet": "4.6",
            "havlak.HavlakLoopFinder.processEdges": "3.4",
            "som.IdentitySet.contains": "4.3",
            "som.Set.contains": "4.0"
        },
        "JProfiler_Mandelbrot.txt": {
            "Run.reportBenchmark": "0.1",
            " ": "0",
            "java.io.PrintStream.println": "0.0",
            "java.lang.ClassLoader.loadClass": "0.0",
            "Mandelbrot.mandelbrot": "99.7",
            "Run.runBenchmark": "0.0",
            "Run.printResult": "0.0"
        },
        "JProfiler_Richards.txt": {
            "Run.reportBenchmark": "0.0",
            "richards.Scheduler.schedule": "16.0",
            "java.io.PrintStream.println": "0.0",
            "richards.Packet.<init>": "0.2",
            "java.lang.ClassLoader.loadClass": "0.0",
            "richards.Scheduler.createIdler": "0.0",
            "Run.runBenchmark": "0.0",
            "richards.TaskControlBlock.runTask": "82.5",
            "richards.RBObject.<init>": "0.4",
            "richards.RBObject.append": "0.6"
        },
        "JProfiler_Bounce.txt": {
            "Run.reportBenchmark": "0.0",
            "java.lang.ClassLoader.loadClass": "0.1",
            "Run.measure": "0.0",
            "java.lang.Integer.valueOf": "0.3",
            "Run.runBenchmark": "0.0",
            "Run.printTotal": "0.0",
            "som.Random.<init>": "1.0",
            "Bounce.benchmark": "52.3",
            "Bounce$Ball.<init>": "46.2",
            "Bounce.lambda$benchmark$0": "0.0"
        },
        "JProfiler_CD.txt": {
            "cd.CollisionDetector.recurse": "2.4",
            "som.Vector.<init>": "6.1",
            "cd.Vector3D.<init>": "7.6",
            "cd.RedBlackTree.treeInsert": "2.2",
            "cd.RedBlackTree.findNode": "1.6",
            "cd.Vector2D.<init>": "44.2",
            "cd.RedBlackTree$InsertResult.<init>": "15.4",
            "cd.RedBlackTree$Node.<init>": "8.0",
            "cd.RedBlackTree$Entry.<init>": "4.9",
            "cd.Motion.<init>": "1.5"
        },
        "JProfiler_NBody.txt": {
            "Run.reportBenchmark": "0.2",
            " ": "0",
            "java.io.PrintStream.println": "0.1",
            "Run.runBenchmark": "0.2",
            "NBody.innerBenchmarkLoop": "0.6",
            "nbody.NBodySystem.advance": "98.9",
            "Run.printResult": "0.2"
        },
        "JProfiler_Permute.txt": {
            "Permute.permute": "98.6",
            "Run.reportBenchmark": "0.1",
            " ": "0",
            "Permute.benchmark": "0.7",
            "java.io.PrintStream.println": "0.2",
            "java.lang.ClassLoader.loadClass": "0.1",
            "java.lang.Integer.valueOf": "0.3",
            "Run.runBenchmark": "0.1",
            "Run.printResult": "0.1"
        },
        "JProfiler_List.txt": {
            "Run.reportBenchmark": "0.1",
            "java.io.PrintStream.println": "0.1",
            "List.makeList": "0.4",
            "java.lang.ClassLoader.loadClass": "0.1",
            "Run.runBenchmark": "0.1",
            "List.tail": "2.1",
            "List$Element.length": "0.1",
            "List.isShorterThan": "77.3",
            "List$Element.<init>": "19.3",
            "Run.printResult": "0.4"
        },
        "JProfiler_Storage.txt": {
            "Run.reportBenchmark": "0.0",
            "java.io.PrintStream.println": "0.0",
            "java.lang.ClassLoader.loadClass": "0.0",
            "Storage.lambda$buildTreeDepth$0": "0.6",
            "Run.runBenchmark": "0.0",
            "java.lang.Integer.valueOf": "0.0",
            "som.Random.<init>": "0.0",
            "Storage.buildTreeDepth": "99.3",
            "Benchmark.innerBenchmarkLoop": "0.0",
            "Run.printResult": "0.0"
        },
        "JProfiler_Json.txt": {
            "json.JsonPureStringParser.readObject": "0.9",
            "json.JsonPureStringParser.readNumber": "0.1",
            "json.JsonObject$HashIndexTable.<init>": "0.5",
            "som.Vector.<init>": "2.7",
            "java.lang.String.substring": "91.4",
            "json.JsonValue.<init>": "3.8",
            "json.JsonPureStringParser.readArray": "0.3",
            "json.JsonPureStringParser.readStringInternal": "0.1",
            "json.JsonPureStringParser.readString": "0.0",
            "json.JsonPureStringParser.readValue": "0.2"
        },
        "JProfiler_Queens.txt": {
            "Run.reportBenchmark": "0.1",
            " ": "0",
            "java.util.Arrays.fill": "0.3",
            "java.io.PrintStream.println": "0.1",
            "Queens.queens": "23.7",
            "Queens.placeQueen": "75.6",
            "Run.runBenchmark": "0.1",
            "Run.getSuiteFromName": "0.1",
            "Harness.processArguments": "0.1",
            "java.util.Arrays.fill0": "0.1"
        }
    },
    "YourKit": {
        "YourKit_Json.txt": {
            "java.lang.String.equals(Object) String.java": "24.01870931041022",
            "java.lang.String.<init>(byte[], byte) String.java": "7.188757558519268",
            "json.JsonPureStringParser.isWhiteSpace()": "2.0647662389650887",
            "json.JsonPureStringParser.read()": "21.35558224301035",
            "java.lang.String.length() String.java": "3.4131850072688206",
            "java.util.Arrays.copyOfRange(byte[], int, int) Arrays.java": "2.781113709626446",
            "java.lang.String.substring(int, int) String.java": "9.173461433116325",
            "java.lang.StringLatin1.newString(byte[], int, int) StringLatin1.java": "7.020205212481303",
            "json.JsonPureStringParser.readStringInternal()": "2.8401070307397345",
            "json.JsonPureStringParser.readValue()": "2.2038219244464115"
        },
        "YourKit_Havlak.txt": {
            "som.Vector.forEach(ForEachInterface)": "8.631851532153647",
            "havlak.HavlakLoopFinder.doDFS(BasicBlock, int)": "4.315925766076823",
            "havlak.HavlakLoopFinder.findLoops()": "21.79542511868796",
            "som.Vector.<init>(int)": "5.394907207596029",
            "jdk.internal.org.objectweb.asm.FieldWriter.putFieldInfo(ByteVector) FieldWriter.java": "5.394907207596029",
            "havlak.SimpleLoop.<init>(BasicBlock, boolean)": "3.452740612861459",
            "havlak.HavlakLoopFinder$$Lambda$19.0x00000008000cc428.apply(Object)": "4.9633146309883465",
            "som.Vector.at(int)": "4.100129477772982",
            "jdk.internal.misc.Unsafe.allocateInstance(Class) Unsafe.java (native)": "13.595166163141991",
            "som.IdentitySet.lambda$contains$0(Object, Object)": "6.473888649115235"
        },
        "YourKit_Queens.txt": {
            "Queens.placeQueen(int)": "12.431495185311329",
            "java.io.FileOutputStream.writeBytes(byte[], int, int, boolean) FileOutputStream.java (native)": "0.15481314053936895",
            "sun.nio.fs.UnixFileAttributeViews.createBasicView(UnixPath, boolean) UnixFileAttributeViews.java": "0.21673839675511655",
            "Queens.getRowColumn(int, int)": "59.21602625630863",
            "Queens.queens()": "0.29414496702480103",
            "java.util.Arrays.fill(boolean[], boolean) Arrays.java": "0.44895810756417",
            "java.lang.Class.getDeclaredFields0(boolean) Class.java (native)": "0.17029445459330586",
            "Queens.setRowColumn(int, int, boolean)": "25.389355048456512",
            "java.lang.ClassLoader.findBootstrapClass(String) ClassLoader.java (native)": "0.44895810756417",
            "java.util.Arrays.fill(int[], int) Arrays.java": "0.29414496702480103"
        },
        "YourKit_Richards.txt": {
            "richards.TaskState.isTaskHoldingOrWaiting()": "3.0520837541732013",
            "richards.HandlerTaskDataRecord.workInAdd(Packet)": "1.9465756795569154",
            "richards.TaskControlBlock.runTask()": "39.05638825737404",
            "richards.Scheduler$$Lambda$15.0x00000008000c7b98.apply(Packet, RBObject)": "4.40734116126094",
            "richards.Scheduler.schedule()": "2.3028357567588413",
            "richards.Scheduler.lambda$createDevice$0(Packet, RBObject)": "1.2450738780562156",
            "richards.RBObject.append(Packet, Packet)": "4.910512610504898",
            "richards.Scheduler$$Lambda$14.0x00000008000c7970.apply(Packet, RBObject)": "2.886808460625916",
            "Richards.benchmark()": "25.937202734020637",
            "richards.TaskControlBlock.addInputAndCheckPriority(Packet, TaskControlBlock)": "1.3736213285929932"
        },
        "YourKit_Storage.txt": {
            "java.util.LinkedHashMap.linkNodeLast(LinkedHashMap$Entry) LinkedHashMap.java": "0.10178771368723316",
            "java.lang.invoke.DirectMethodHandle.allocateInstance(Object) DirectMethodHandle.java": "0.31607763723930293",
            "java.lang.invoke.LambdaForm$DMH.0x00000008000c5400.newInvokeSpecial(Object, Object, int, Object) LambdaForm$DMH": "1.2268098123355995",
            "Storage$$Lambda$12.0x00000008000c2a98.apply(int)": "0.9000176789186931",
            "java.util.AbstractList.hashCode() AbstractList.java": "0.11250220986483664",
            "java.util.Arrays.setAll(Object[], IntFunction) Arrays.java": "41.44902846305909",
            "som.Random.next()": "16.01281453742841",
            "java.util.jar.Attributes.<init>(int) Attributes.java": "0.08035872133202616",
            "Storage.buildTreeDepth(int, Random)": "36.63286243122633",
            "Storage.lambda$buildTreeDepth$0(int, Random, int)": "2.914342960308149"
        },
        "YourKit_Towers.txt": {
            "Towers.pushDisk(Towers$TowersDisk, int)": "33.863307867024574",
            "Towers.popDiskFrom(int)": "29.55144477778722",
            "Towers.moveDisks(int, int, int)": "9.546829262367758",
            "Towers$TowersDisk.getSize()": "2.2348811504779484",
            "java.lang.invoke.MethodHandles.dropArgumentChecks(MethodType, int, List) MethodHandles.java": "0.32794451664622076",
            "java.lang.invoke.LambdaFormEditor$TransformKey.inRange(int) LambdaFormEditor.java": "0.07287655925471571",
            "Towers.moveTopDisk(int, int)": "8.065005890855206",
            "Benchmark.innerBenchmarkLoop(int)": "0.10931483888207358",
            "com.sun.management.internal.GarbageCollectionNotifInfoCompositeData.getCompositeTypeByBuilder() GarbageCollectionNotifInfoCompositeData.java": "0.14575311850943143",
            "Towers$TowersDisk.setNext(Towers$TowersDisk)": "15.972112569991861"
        },
        "YourKit_Permute.txt": {
            "sun.management.MappedMXBeanType.newMappedType(Type) MappedMXBeanType.java": "0.045058745339236025",
            "jdk.internal.misc.TerminatingThreadLocal$1.initialValue() TerminatingThreadLocal.java": "0.05632343167404503",
            "java.security.Permissions.add(Permission) Permissions.java": "0.16897029502213506",
            "java.util.zip.ZipFile$Source.get(File, boolean, ZipCoder) ZipFile.java": "0.09011749067847205",
            "Permute.permute(int)": "54.228200015770554",
            "java.nio.ByteBuffer.position(int) ByteBuffer.java": "0.10138217701328105",
            "java.nio.CharBuffer.wrap(char[], int, int) CharBuffer.java": "0.1802349813569441",
            "com.yourkit.probes.Table.createRow() a": "0.10138217701328105",
            "Permute.benchmark()": "0.3266759037094612",
            "Permute.swap(int, int)": "44.60815788584366"
        },
        "YourKit_DeltaBlue.txt": {
            "deltablue.Planner.addPropagate(AbstractConstraint, int)": "3.23747375875762",
            "som.Vector.forEach(ForEachInterface)": "39.86139565470319",
            "deltablue.EqualityConstraint.execute()": "3.3386448137187954",
            "deltablue.BinaryConstraint.isSatisfied()": "3.642157978602322",
            "som.Vector.<init>(int)": "7.157852138503175",
            "deltablue.AbstractConstraint.satisfy(int, Planner)": "4.552697473252903",
            "deltablue.Planner.makePlan(Vector)": "2.1498849179249815",
            "som.Vector.append(Object)": "6.297898171333181",
            "deltablue.Variable.setDeterminedBy(AbstractConstraint)": "1.9981283354832184",
            "deltablue.Plan$$Lambda$22.0x00000008000ccd88.apply(Object)": "3.793914561044085"
        },
        "YourKit_List.txt": {
            "sun.nio.cs.StreamEncoder.implWrite(char[], int, int) StreamEncoder.java": "0.14839997841454858",
            "List.tail(List$Element, List$Element, List$Element)": "3.0759268253197343",
            "List$Element.<init>(Object)": "0.2563272354433112",
            "List.makeList(int)": "0.9308725918730774",
            "Benchmark.innerBenchmarkLoop(int)": "0.12141816415735794",
            "java.lang.Class.getDeclaredFields0(boolean) Class.java (native)": "0.02698181425719065",
            "List$Element.getNext()": "25.457341751659378",
            "java.lang.ClassLoader.findBootstrapClass(String) ClassLoader.java (native)": "0.08094544277157195",
            "List.isShorterThan(List$Element, List$Element)": "69.38373536236575",
            "java.util.zip.Inflater.inflateBytesBytes(long, byte[], int, int, byte[], int, int) Inflater.java (native)": "0.5126544708866224"
        },
        "YourKit_NBody.txt": {
            "nbody.Body.getY()": "1.9015270278116472",
            "nbody.Body.getZ()": "5.428787087034778",
            "nbody.Body.getX()": "0.8418974626952329",
            "nbody.Body.setZ(double)": "0.6531963072635429",
            "nbody.NBodySystem.advance(double)": "40.80299599372931",
            "nbody.Body.setVY(double)": "6.4593857051617025",
            "nbody.Body.setVZ(double)": "9.638274400510943",
            "nbody.Body.getVX()": "0.6822272542530337",
            "nbody.Body.setVX(double)": "30.090576554607207",
            "nbody.Body.setY(double)": "1.2918771410323402"
        },
        "YourKit_Mandelbrot.txt": {
            "Mandelbrot.mandelbrot(int)": "99.29739154453017",
            "java.lang.StringConcatHelper.checkOverflow(long) StringConcatHelper.java": "0.0776839815630017",
            "java.lang.invoke.InvokerBytecodeGenerator.<init>(String, String, LambdaForm, MethodType) InvokerBytecodeGenerator.java": "0.017263107014000377",
            "java.lang.invoke.DelegatingMethodHandle$Holder.reinvoke_L(Object, long, Object) DelegatingMethodHandle$Holder": "0.0776839815630017",
            "java.lang.invoke.MethodHandleNatives.resolve(MemberName, Class, int, boolean) MethodHandleNatives.java (native)": "0.034526214028000754",
            "Mandelbrot.verifyResult(int, int)": "0.0776839815630017",
            "java.util.zip.ZipFile$Source.get(File, boolean, ZipCoder) ZipFile.java": "0.04315776753500094",
            "java.lang.ClassLoader.findBootstrapClass(String) ClassLoader.java (native)": "0.06042087454900132",
            "com.yourkit.probes.Table.createRow() a": "0.06905242805600151",
            "java.lang.AbstractStringBuilder.append(char) AbstractStringBuilder.java": "0.2416834981960053"
        },
        "YourKit_CD.txt": {
            "cd.RedBlackTree.leftRotate(RedBlackTree$Node)": "4.3930408174085605",
            "cd.CollisionDetector.isInVoxel(Vector2D, Motion)": "21.66223575480773",
            "cd.RedBlackTree.treeInsert(Comparable, Object)": "16.292122065941054",
            "cd.RedBlackTree.findNode(Comparable)": "8.85424950957001",
            "cd.CollisionDetector.recurse(RedBlackTree, RedBlackTree, Vector2D, Motion)": "9.9373612973104",
            "cd.RedBlackTree.rightRotate(RedBlackTree$Node)": "2.21924303362191",
            "cd.RedBlackTree.put(Comparable, Object)": "5.4382815636195625",
            "cd.Vector2D.compareNumbers(double, double)": "9.036030508911056",
            "cd.RedBlackTree.forEach(ForEachInterface)": "4.332447150961546",
            "cd.CollisionDetector.lambda$handleNewFrame$0(RedBlackTree, Vector, Aircraft)": "2.287410908374802"
        },
        "YourKit_Sieve.txt": {
            "java.lang.AbstractStringBuilder.<init>(String) AbstractStringBuilder.java": "0.04378187868041417",
            "java.util.Arrays.fill(boolean[], boolean) Arrays.java": "3.1632407346599236",
            "sun.nio.fs.UnixFileSystem.<init>(UnixFileSystemProvider, String) UnixFileSystem.java": "0.09850922703093189",
            "Sieve.benchmark()": "88.84437731223046",
            "java.lang.invoke.InvokerBytecodeGenerator.isStaticallyInvocable(MemberName) InvokerBytecodeGenerator.java": "0.08756375736082835",
            "com.yourkit.probes.Table.createRow() a": "0.3502550294433134",
            "java.lang.invoke.LambdaForm$BasicType.basicTypeSlots() LambdaForm.java": "0.08756375736082835",
            "java.lang.reflect.Field.copy() Field.java": "0.12040016637113898",
            "Sieve.sieve(boolean[], int)": "7.0707734068868895",
            "java.lang.String.isLatin1() String.java": "0.09850922703093189"
        },
        "YourKit_Bounce.txt": {
            "java.lang.invoke.DirectMethodHandle$Holder.newInvokeSpecial(Object, Object) DirectMethodHandle$Holder": "0.28193368919630096",
            "Bounce.benchmark()": "66.08525674761295",
            "java.security.Permissions.add(Permission) Permissions.java": "0.18795579279753397",
            "Bounce.lambda$benchmark$0(Random, int)": "1.1089391775054505",
            "som.Random.next()": "0.16916021351778057",
            "com.yourkit.probes.Table.createRow() a": "0.16916021351778057",
            "Bounce$Ball.bounce()": "29.302308097135544",
            "Bounce$Ball.<init>(Random)": "1.6728065558980523",
            "jdk.internal.loader.NativeLibraries$NativeLibraryImpl.find(String) NativeLibraries.java": "0.4135027441545747",
            "java.util.Collections$UnmodifiableSet.equals(Object) Collections.java": "0.16916021351778057"
        }
    },
    "Runtimes": {
        "NBody.data": 104.3185,
        "JavaFlightRecorder_Queens.jfr": 106.6635,
        "rebench_test_Async_Bounce.txt": 101.3735,
        "JavaFlightRecorder_Sieve.jfr": 105.4635,
        "Permute.hpl": 105.77250000000001,
        "CD.data": 96.5925,
        "DeltaBlue.hpl": 90.3865,
        "List.data": 151.12,
        "JavaFlightRecorder_Json.jfr": 85.6515,
        "NBody.hpl": 102.71600000000001,
        "Bounce.hpl": 101.257,
        "Towers.hpl": 109.071,
        "Sieve.data": 105.672,
        "Richards.hpl": 92.8715,
        "JavaFlightRecorder_Havlak.jfr": 163.70850000000002,
        "JavaFlightRecorder_CD.jfr": 96.7775,
        "rebench_test_Async_Mandelbrot.txt": 86.70599999999999,
        "JavaFlightRecorder_DeltaBlue.jfr": 88.58449999999999,
        "JavaFlightRecorder_Towers.jfr": 109.868,
        "rebench_test_Async_CD.txt": 94.902,
        "rebench_test_Async_Permute.txt": 104.4305,
        "Mandelbrot.data": 85.52799999999999,
        "rebench_test_Async_NBody.txt": 102.4255,
        "JavaFlightRecorder_Permute.jfr": 106.905,
        "JavaFlightRecorder_Bounce.jfr": 103.20349999999999,
        "Havlak.data": 157.3995,
        "Mandelbrot.hpl": 85.143,
        "JavaFlightRecorder_Storage.jfr": 103.2795,
        "List.hpl": 155.27499999999998,
        "rebench_test_Async_Towers.txt": 110.5875,
        "Queens.hpl": 111.492,
        "JavaFlightRecorder_NBody.jfr": 103.505,
        "Storage.data": 116.0055,
        "rebench_test_Async_Sieve.txt": 104.76750000000001,
        "JavaFlightRecorder_Richards.jfr": 92.03200000000001,
        "Storage.hpl": 108.984,
        "rebench_test_Async_List.txt": 149.7095,
        "Bounce.data": 103.406,
        "rebench_test_Async_Richards.txt": 97.5925,
        "Permute.data": 105.1725,
        "rebench_test_Async_DeltaBlue.txt": 81.6695,
        "JavaFlightRecorder_Mandelbrot.jfr": 88.3085,
        "JavaFlightRecorder_List.jfr": 149.21949999999998,
        "DeltaBlue.data": 84.06700000000001,
        "Queens.data": 111.572,
        "rebench_test_Async_Storage.txt": 108.8785,
        "Json.hpl": 81.91550000000001,
        "Towers.data": 112.2315,
        "Havlak.hpl": 157.8545,
        "Richards.data": 93.39699999999999,
        "rebench_test_Async_Havlak.txt": 160.51600000000002,
        "Sieve.hpl": 104.592,
        "CD.hpl": 93.7045,
        "rebench_test_Async_Json.txt": 80.64,
        "Json.data": 81.776,
        "rebench_test_Async_Queens.txt": 105.339
    },
    "Perf": {
        "NBody.data": {
            " ": "0",
            "x86_pmu_disable_all": "0.03%",
            "[.] Interpreter": "0.11%",
            "[.] boolean NBody.innerBenchmarkLoop(int)": "0.24%",
            "asm_sysvec_apic_timer_interrupt": "0.03%",
            "[.] void nbody.NBodySystem.advance(double)": "99.09%"
        },
        "Permute.data": {
            " ": "0",
            "x86_pmu_disable_all": "0.01%",
            "[.] Interpreter": "0.10%",
            "[.] boolean Benchmark.innerBenchmarkLoop(int)": "0.13%",
            "[.] void Permute.permute(int)": "0.01%"
        },
        "Havlak.data": {
            " ": "0",
            "[.] void havlak.LoopStructureGraph$$Lambda$12/0x0000000801009f90.apply(java.lang.Object)": "34.28%",
            "[.] int havlak.HavlakLoopFinder.doDFS(havlak.BasicBlock, int)": "5.87%",
            "[.] void havlak.HavlakLoopFinder$$Lambda$3/0x0000000801008a28.apply(java.lang.Object)": "8.06%",
            "[.] void havlak.HavlakLoopFinder$$Lambda$8/0x00000008010096f0.apply(java.lang.Object)": "5.07%",
            "[.] void havlak.HavlakLoopFinder.findLoops()": "21.40%"
        },
        "DeltaBlue.data": {
            "[.] void deltablue.ScaleConstraint.execute()": "6.71%",
            " ": "0",
            "[.] void deltablue.Plan$$Lambda$8/0x000000080100d938.apply(java.lang.Object)": "11.06%",
            "[.] som.Vector deltablue.Planner.removePropagateFrom(deltablue.Variable)": "5.49%",
            "[.] void deltablue.Planner.chainTest(int)": "29.68%",
            "[.] deltablue.Plan deltablue.Planner.makePlan(som.Vector)": "5.02%"
        },
        "Queens.data": {
            " ": "0",
            "[.] boolean Queens.queens()": "2.66%",
            "[.] Interpreter": "0.10%",
            "[.] boolean Benchmark.innerBenchmarkLoop(int)": "0.21%",
            "[.] boolean Queens.placeQueen(int)": "96.34%",
            "clear_page_rep": "0.07%"
        },
        "Towers.data": {
            " ": "0",
            "[.] Interpreter": "0.12%",
            "[.] void Towers.moveDisks(int, int, int)": "0.02%",
            "[.] boolean Benchmark.innerBenchmarkLoop(int)": "0.08%",
            "clear_page_rep": "0.03%"
        },
        "Richards.data": {
            " ": "0",
            "[.] vtable chunks": "37.09%",
            "[.] boolean richards.Scheduler.start()": "22.85%",
            "[.] richards.TaskControlBlock richards.Scheduler$$Lambda$5/0x0000000801006c50.apply(richards.Packet, richards.RBObject)": "6.60%",
            "[.] richards.TaskControlBlock richards.Scheduler$$Lambda$4/0x0000000801006a28.apply(richards.Packet, richards.RBObject)": "12.72%",
            "[.] void richards.Scheduler.schedule()": "7.90%"
        },
        "Storage.data": {
            " ": "0",
            "[.] java.lang.Object Storage.buildTreeDepth(int, som.Random)": "9.55%",
            "x86_pmu_disable_all": "0.12%",
            "[.] Interpreter": "0.10%",
            "clear_page_rep": "0.09%",
            "[.] void java.util.Arrays.setAll(java.lang.Object[], java.util.function.IntFunction)": "87.52%"
        },
        "CD.data": {
            " ": "0",
            "[.] cd.RedBlackTree$InsertResult cd.RedBlackTree.treeInsert(java.lang.Comparable, java.lang.Object)": "26.04%",
            "[.] void cd.RedBlackTree.forEach(som.ForEachInterface)": "19.62%",
            "[.] boolean cd.CollisionDetector.isInVoxel(cd.Vector2D, cd.Motion)": "13.28%",
            "[.] java.lang.Object cd.RedBlackTree.put(java.lang.Comparable, java.lang.Object)": "11.52%",
            "[.] void cd.CollisionDetector$$Lambda$5/0x000000080100c450.apply(java.lang.Object)": "10.17%"
        },
        "Mandelbrot.data": {
            " ": "0",
            "[.] Interpreter": "0.14%",
            "[.] int Mandelbrot.mandelbrot(int)": "0.02%"
        },
        "List.data": {" ": "0"},
        "Sieve.data": {
            " ": "0",
            "x86_pmu_disable_all": "0.11%",
            "[.] Interpreter": "0.15%",
            "[.] boolean Benchmark.innerBenchmarkLoop(int)": "93.85%",
            "[.] java.lang.Object Sieve.benchmark()": "1.87%",
            "[.] int Sieve.sieve(boolean[], int)": "2.25%"
        },
        "Bounce.data": {
            " ": "0",
            "x86_pmu_disable_all": "0.07%",
            "[.] Interpreter": "0.13%",
            "[.] boolean Benchmark.innerBenchmarkLoop(int)": "92.89%",
            "clear_page_rep": "0.07%",
            "[.] java.lang.Object Bounce.benchmark()": "5.78%"
        },
        "Json.data": {
            "[.] java.lang.String json.JsonPureStringParser.readStringInternal()": "32.51%",
            " ": "0",
            "[.] json.JsonValue json.JsonPureStringParser.readNull()": "4.50%",
            "[.] StubRoutines (2)": "7.98%",
            "[.] json.JsonArray json.JsonPureStringParser.readArray()": "19.84%",
            "[.] json.JsonValue json.JsonPureStringParser.readValue()": "20.88%"
        }
    }
}